README.md
setup.py
nbimport/__init__.py
nbimport.egg-info/PKG-INFO
nbimport.egg-info/SOURCES.txt
nbimport.egg-info/dependency_links.txt
nbimport.egg-info/not-zip-safe
nbimport.egg-info/top_level.txt